cmonkey/BSCM.py
cmonkey/__init__.py
cmonkey/cmonkey_run.py
cmonkey/config.py
cmonkey/database.py
cmonkey/datamatrix.py
cmonkey/debug.py
cmonkey/membership.py
cmonkey/meme_suite.py
cmonkey/microarray.py
cmonkey/microbes_online.py
cmonkey/motif.py
cmonkey/network.py
cmonkey/organism.py
cmonkey/patches.py
cmonkey/pssm.py
cmonkey/rsat.py
cmonkey/schedule.py
cmonkey/scoring.py
cmonkey/seqtools.py
cmonkey/set_enrichment.py
cmonkey/stringdb.py
cmonkey/thesaurus.py
cmonkey/util.py
cmonkey/weeder.py
cmonkey/weederlauncher.py
cmonkey/cmviewer/__init__.py
cmonkey/cmviewer/webapp.py
cmonkey/cmviewer/static/images/back_disabled.png
cmonkey/cmviewer/static/images/back_enabled.png
cmonkey/cmviewer/static/images/back_enabled_hover.png
cmonkey/cmviewer/static/images/cmonkey2_logo.png
cmonkey/cmviewer/static/images/favicon.ico
cmonkey/cmviewer/static/images/favicon.png
cmonkey/cmviewer/static/images/forward_disabled.png
cmonkey/cmviewer/static/images/forward_enabled.png
cmonkey/cmviewer/static/images/forward_enabled_hover.png
cmonkey/cmviewer/static/images/isb_logo.png
cmonkey/cmviewer/static/images/sort_asc.png
cmonkey/cmviewer/static/images/sort_asc_disabled.png
cmonkey/cmviewer/static/images/sort_both.png
cmonkey/cmviewer/static/images/sort_desc.png
cmonkey/cmviewer/static/images/sort_desc_disabled.png
cmonkey/cmviewer/static/javascripts/arbor.js
cmonkey/cmviewer/static/javascripts/cmviewer_util.js
cmonkey/cmviewer/static/javascripts/cola.adaptor.js
cmonkey/cmviewer/static/javascripts/cola.v3.min.js
cmonkey/cmviewer/static/javascripts/cytoscape.min.js
cmonkey/cmviewer/static/javascripts/dagre.js
cmonkey/cmviewer/static/javascripts/gene_annotations.js
cmonkey/cmviewer/static/javascripts/highcharts-more.js
cmonkey/cmviewer/static/javascripts/highcharts.js
cmonkey/cmviewer/static/javascripts/jquery-2.1.1.min.js
cmonkey/cmviewer/static/javascripts/jquery.dataTables.min.js
cmonkey/cmviewer/static/javascripts/raphael-min.js
cmonkey/cmviewer/static/javascripts/seqlogo.js
cmonkey2-1.2.16.dist-info/LICENSE
cmonkey2-1.2.16.dist-info/METADATA
cmonkey2-1.2.16.dist-info/WHEEL
cmonkey2-1.2.16.dist-info/top_level.txt
cmonkey2-1.2.16.dist-info/RECORD
