Metadata-Version: 2.1
Name: cmonkey2
Version: 1.2.16
Summary: cmonkey2 is an implementation of the cmonkey biclustering method in Python
Home-page: https://github.com/baliga-lab/cmonkey2
Author: Baliga Lab, Institute for Systems Biology
Author-email: wwu@systemsbiology.net
Maintainer: Baliga Lab, Institute for Systems Biology
Maintainer-email: wwu@systemsbiology.net
License: LGPL V3
Keywords: class,cmonkey2
Classifier: Development Status :: 5 - Production/Stable
Classifier: Environment :: Console
Classifier: Intended Audience :: Science/Research
Classifier: Natural Language :: English
Classifier: License :: OSI Approved :: GNU Lesser General Public License v3 or later (LGPLv3+)
Classifier: Operating System :: OS Independent
Classifier: Programming Language :: Python
Classifier: Programming Language :: Python :: 2
Classifier: Programming Language :: Python :: 2.7
Classifier: Programming Language :: Python :: 3
Classifier: Programming Language :: Python :: 3.5
Classifier: Programming Language :: Python :: Implementation :: CPython
Classifier: Topic :: Scientific/Engineering :: Bio-Informatics
Classifier: Topic :: Software Development :: Libraries :: Python Modules
License-File: LICENSE
Requires-Dist: numpy
Requires-Dist: scipy
Requires-Dist: rpy2 <=2.8.6
Requires-Dist: beautifulsoup4
Requires-Dist: configparser
Requires-Dist: pandas
Requires-Dist: biopython
Requires-Dist: lxml
Requires-Dist: cherrypy
Requires-Dist: cherrypy-cors
Requires-Dist: jinja2
Requires-Dist: routes
Requires-Dist: svgwrite
Requires-Dist: sqlalchemy
Requires-Dist: sqlalchemy-utils
